{
   "deck1": {
      "name": "goat-control.ydk",
      "cardsFound": [
         "Black Luster Soldier - Envoy of the Beginning",
         "D.D. Warrior Lady",
         "Dark Magician of Chaos",
         "Dekoichi the Battlechanted Locomotive",
         "Dekoichi the Battlechanted Locomotive",
         "Fusilier Dragon, the Dual-Mode Beast",
         "Magical Merchant",
         "Magician of Faith",
         "Magician of Faith",
         "Morphing Jar",
         "Sangan",
         "Sinister Serpent",
         "Tribe-Infecting Virus",
         "Tsukuyomi",
         "Zaborg the Thunder Monarch",
         "Book of Moon",
         "Creature Swap",
         "Giant Trunade",
         "Graceful Charity",
         "Heavy Storm",
         "Nobleman of Crossout",
         "Nobleman of Crossout",
         "Pot of Greed",
         "Premature Burial",
         "Scapegoat",
         "Scapegoat",
         "Snatch Steal",
         "Jar of Greed",
         "Mirror Force",
         "Ring of Destruction",
         "Solemn Judgment",
         "Trap Dustshoot",
         "Thousand-Eyes Restrict",
         "A Bountiful Ocean"
      ],
      "cardsNotFound": [
         "Delinquent Duo",
         "Metamorphosis",
         "Metamorphosis",
         "Metamorphosis",
         "Upstart Goblin",
         "Upstart Goblin",
         "Solemn Judgment",
         "Trap Dustshoot",
         "Dark Balter the Terrible",
         "Dark Blade the Dragon Knight",
         "Darkfire Dragon",
         "Dragoness the Wicked Knight",
         "Fiend Skull Dragon",
         "Gatling Dragon",
         "Gatling Dragon",
         "King Dragun",
         "Reaper on the Nightmare",
         "Ryu Senshi",
         "The Last Warrior from Another Planet",
         "Thousand-Eyes Restrict",
         "Thousand-Eyes Restrict",
         "Twin-Headed Thunder Dragon"
      ],
      "completed": 60.71428571428571
   },
   "deck2": {
      "name": "warrior.ydk",
      "cardsFound": [
         "Black Luster Soldier - Envoy of the Beginning",
         "D.D. Warrior Lady",
         "Dark Magician of Chaos",
         "Dekoichi the Battlechanted Locomotive",
         "Dekoichi the Battlechanted Locomotive",
         "Magical Merchant",
         "Magician of Faith",
         "Magician of Faith",
         "Morphing Jar",
         "Sangan",
         "Sinister Serpent",
         "Zaborg the Thunder Monarch",
         "Book of Moon",
         "Creature Swap",
         "Giant Trunade",
         "Graceful Charity",
         "Heavy Storm",
         "Nobleman of Crossout",
         "Nobleman of Crossout",
         "Pot of Greed",
         "Premature Burial",
         "Scapegoat",
         "Scapegoat",
         "Snatch Steal",
         "Jar of Greed",
         "Mirror Force",
         "Ring of Destruction",
         "A Bountiful Ocean"
      ],
      "cardsNotFound": [
         "Fusilier Dragon, the Dual-Mode Beast",
         "Tribe-Infecting Virus",
         "Tsukuyomi",
         "Delinquent Duo",
         "Metamorphosis",
         "Metamorphosis",
         "Metamorphosis",
         "Upstart Goblin",
         "Upstart Goblin",
         "Solemn Judgment",
         "Solemn Judgment",
         "Trap Dustshoot",
         "Trap Dustshoot",
         "Dark Balter the Terrible",
         "Dark Blade the Dragon Knight",
         "Darkfire Dragon",
         "Dragoness the Wicked Knight",
         "Fiend Skull Dragon",
         "Gatling Dragon",
         "Gatling Dragon",
         "King Dragun",
         "Reaper on the Nightmare",
         "Ryu Senshi",
         "The Last Warrior from Another Planet",
         "Thousand-Eyes Restrict",
         "Thousand-Eyes Restrict",
         "Thousand-Eyes Restrict",
         "Twin-Headed Thunder Dragon"
      ],
      "completed": 50
   }
}